flags.py
py_flags-1.1.3.dist-info/LICENSE.txt
py_flags-1.1.3.dist-info/METADATA
py_flags-1.1.3.dist-info/WHEEL
py_flags-1.1.3.dist-info/top_level.txt
py_flags-1.1.3.dist-info/RECORD
