Metadata-Version: 2.1
Name: py-flags
Version: 1.1.3
Summary: Type-safe (bit)flags for python 3
Home-page: https://github.com/pasztorpisti/py-flags
Author: István Pásztor
Author-email: pasztorpisti@gmail.com
License: MIT
Keywords: flags bit flag set bitfield bool arithmetic
Platform: UNKNOWN
Classifier: License :: OSI Approved :: MIT License
Classifier: Development Status :: 5 - Production/Stable
Classifier: Intended Audience :: Developers
Classifier: Topic :: Software Development :: Libraries :: Python Modules
Classifier: Programming Language :: Python :: 3
Classifier: Programming Language :: Python :: Implementation :: CPython
Classifier: Programming Language :: Python :: Implementation :: PyPy
Requires-Dist: dictionaries (==0.0.1)
